{"_path":"/games/devil-may-cry","_dir":"games","_draft":false,"_partial":false,"_locale":"","title":"鬼泣5 - 相机系统分析","description":"经典Stylish Action的动态相机设计：非锁定为主、战斗自动构图、华丽演出镜头","game":"Devil May Cry 5","developer":"CAPCOM","genre":"动作","platform":["PS4","PS5","Xbox","PC"],"camera_type":["TPS","Lock-on","Dynamic"],"tags":["combat","lock-on","stylish-action","auto-camera"],"date":"2026-03-06","status":"in-progress","cover":"","body":{"type":"root","children":[{"type":"element","tag":"h2","props":{"id":"概述"},"children":[{"type":"text","value":"概述"}]},{"type":"element","tag":"p","props":{},"children":[{"type":"text","value":"鬼泣5是卡普空开发的经典Stylish Action游戏，以快节奏战斗和华丽连招著称。其相机系统最大的特征是"},{"type":"element","tag":"strong","props":{},"children":[{"type":"text","value":"以非锁定为默认状态"}]},{"type":"text","value":"，通过智能的自动相机调整来辅助战斗，而非依赖传统的硬锁定视角。"}]},{"type":"element","tag":"p","props":{},"children":[{"type":"text","value":"DMC5的相机在系列中做了显著进化——从早期固定机位转向了完全自由的第三人称跟随相机，但保留了系列标志性的\"戏剧化镜头语言\"。"}]},{"type":"element","tag":"h3","props":{"id":"核心设计理念"},"children":[{"type":"text","value":"核心设计理念"}]},{"type":"element","tag":"ul","props":{},"children":[{"type":"element","tag":"li","props":{},"children":[{"type":"element","tag":"strong","props":{},"children":[{"type":"text","value":"自由视角为主"}]},{"type":"text","value":"：玩家可完全自由控制相机，不强制锁定"}]},{"type":"element","tag":"li","props":{},"children":[{"type":"element","tag":"strong","props":{},"children":[{"type":"text","value":"软锁定辅助"}]},{"type":"text","value":"：战斗中相机自动偏向敌人方向，但不限制移动"}]},{"type":"element","tag":"li","props":{},"children":[{"type":"element","tag":"strong","props":{},"children":[{"type":"text","value":"演出优先"}]},{"type":"text","value":"：大招、处决、Boss战切换演出镜头，强调视觉表现力"}]}]},{"type":"element","tag":"h2","props":{"id":"探索相机"},"children":[{"type":"text","value":"探索相机"}]},{"type":"element","tag":"h3","props":{"id":"跟随逻辑"},"children":[{"type":"text","value":"跟随逻辑"}]},{"type":"element","tag":"ul","props":{},"children":[{"type":"element","tag":"li","props":{},"children":[{"type":"text","value":"标准第三人称越肩视角，角色偏左约1/3屏"}]},{"type":"element","tag":"li","props":{},"children":[{"type":"text","value":"弹簧臂跟随，角色急停时相机有明显的惯性延迟"}]},{"type":"element","tag":"li","props":{},"children":[{"type":"text","value":"移动方向改变时相机平滑追赶，约0.3-0.5秒完成"}]}]},{"type":"element","tag":"h3","props":{"id":"视角操控"},"children":[{"type":"text","value":"视角操控"}]},{"type":"element","tag":"ul","props":{},"children":[{"type":"element","tag":"li","props":{},"children":[{"type":"text","value":"右摇杆完全自由控制水平+垂直旋转"}]},{"type":"element","tag":"li","props":{},"children":[{"type":"text","value":"灵敏度可调，默认中等偏快"}]},{"type":"element","tag":"li","props":{},"children":[{"type":"text","value":"无自动回正机制（探索状态下相机不会自动回到角色背后）"}]}]},{"type":"element","tag":"h3","props":{"id":"碰撞处理"},"children":[{"type":"text","value":"碰撞处理"}]},{"type":"element","tag":"ul","props":{},"children":[{"type":"element","tag":"li","props":{},"children":[{"type":"text","value":"相机碰到墙壁时向角色方向推近"}]},{"type":"element","tag":"li","props":{},"children":[{"type":"text","value":"推近过程较为生硬，有时会出现\"贴脸\"的问题"}]},{"type":"element","tag":"li","props":{},"children":[{"type":"text","value":"碰撞恢复（离开墙壁后回到原始距离）有轻微延迟"}]}]},{"type":"element","tag":"h3","props":{"id":"室内狭窄空间"},"children":[{"type":"text","value":"室内/狭窄空间"}]},{"type":"element","tag":"ul","props":{},"children":[{"type":"element","tag":"li","props":{},"children":[{"type":"text","value":"狭窄走廊中相机会自动拉近距离"}]},{"type":"element","tag":"li","props":{},"children":[{"type":"text","value":"部分关卡特定区域使用预设相机角度（继承了经典DMC的设计）"}]},{"type":"element","tag":"li","props":{},"children":[{"type":"text","value":"走廊转角处偶尔出现视角突变"}]}]},{"type":"element","tag":"h2","props":{"id":"战斗相机"},"children":[{"type":"text","value":"战斗相机"}]},{"type":"element","tag":"h3","props":{"id":"锁定系统"},"children":[{"type":"text","value":"锁定系统"}]},{"type":"element","tag":"p","props":{},"children":[{"type":"text","value":"DMC5的锁定系统是其战斗体验的核心组成部分："}]},{"type":"element","tag":"ul","props":{},"children":[{"type":"element","tag":"li","props":{},"children":[{"type":"element","tag":"strong","props":{},"children":[{"type":"text","value":"R1/RB"}]},{"type":"text","value":" 触发硬锁定，锁定后角色面朝目标"}]},{"type":"element","tag":"li","props":{},"children":[{"type":"text","value":"锁定状态下移动变为"},{"type":"element","tag":"strong","props":{},"children":[{"type":"text","value":"相对于敌人的方向输入"}]},{"type":"text","value":"（前=靠近，后=远离）"}]},{"type":"element","tag":"li","props":{},"children":[{"type":"text","value":"锁定时相机距离略微拉远，确保角色和目标同时在画面内"}]},{"type":"element","tag":"li","props":{},"children":[{"type":"element","tag":"strong","props":{},"children":[{"type":"text","value":"锁定不改变相机朝向"}]},{"type":"text","value":"：相机仍然可以自由旋转，锁定只影响角色朝向"}]}]},{"type":"element","tag":"h3","props":{"id":"非锁定状态"},"children":[{"type":"text","value":"非锁定状态"}]},{"type":"element","tag":"p","props":{},"children":[{"type":"text","value":"这是DMC5战斗的"},{"type":"element","tag":"strong","props":{},"children":[{"type":"text","value":"默认和推荐状态"}]},{"type":"text","value":"："}]},{"type":"element","tag":"ul","props":{},"children":[{"type":"element","tag":"li","props":{},"children":[{"type":"text","value":"相机有轻微的\"软朝向\"——自动微调朝向最近的敌人"}]},{"type":"element","tag":"li","props":{},"children":[{"type":"text","value":"攻击方向由摇杆输入决定，而非相机朝向"}]},{"type":"element","tag":"li","props":{},"children":[{"type":"text","value":"群战时相机会尝试略微拉远以纳入更多敌人"}]}]},{"type":"element","tag":"h3","props":{"id":"目标切换"},"children":[{"type":"text","value":"目标切换"}]},{"type":"element","tag":"ul","props":{},"children":[{"type":"element","tag":"li","props":{},"children":[{"type":"text","value":"锁定状态下用右摇杆切换目标"}]},{"type":"element","tag":"li","props":{},"children":[{"type":"text","value":"切换逻辑基于"},{"type":"element","tag":"strong","props":{},"children":[{"type":"text","value":"屏幕空间距离"}]},{"type":"text","value":"而非世界距离"}]},{"type":"element","tag":"li","props":{},"children":[{"type":"text","value":"切换时相机无强制移动，仅角色朝向改变"}]}]},{"type":"element","tag":"h3","props":{"id":"镜头抖动与反馈"},"children":[{"type":"text","value":"镜头抖动与反馈"}]},{"type":"element","tag":"ul","props":{},"children":[{"type":"element","tag":"li","props":{},"children":[{"type":"text","value":"重击命中时有轻微的相机震动（camera shake）"}]},{"type":"element","tag":"li","props":{},"children":[{"type":"text","value":"顿帧（hit-stop）是主要的打击反馈手段，相机shake为辅"}]},{"type":"element","tag":"li","props":{},"children":[{"type":"text","value":"不同招式的shake强度有差异，大招/终结技更强"}]}]},{"type":"element","tag":"h2","props":{"id":"特殊相机"},"children":[{"type":"text","value":"特殊相机"}]},{"type":"element","tag":"h3","props":{"id":"过场演出"},"children":[{"type":"text","value":"过场演出"}]},{"type":"element","tag":"ul","props":{},"children":[{"type":"element","tag":"li","props":{},"children":[{"type":"text","value":"无缝切入/切出的实时过场（非预渲染）"}]},{"type":"element","tag":"li","props":{},"children":[{"type":"text","value":"Boss登场、关卡转换时使用电影化镜头"}]},{"type":"element","tag":"li","props":{},"children":[{"type":"text","value":"过场中大量使用低角度仰拍、慢动作、荷兰角等手法"}]}]},{"type":"element","tag":"h3","props":{"id":"qte处决"},"children":[{"type":"text","value":"QTE/处决"}]},{"type":"element","tag":"ul","props":{},"children":[{"type":"element","tag":"li","props":{},"children":[{"type":"text","value":"处决演出时切换为"},{"type":"element","tag":"strong","props":{},"children":[{"type":"text","value":"预设电影镜头轨道"}]}]},{"type":"element","tag":"li","props":{},"children":[{"type":"text","value":"镜头围绕角色和敌人做动态环绕运动"}]},{"type":"element","tag":"li","props":{},"children":[{"type":"text","value":"演出结束后平滑过渡回游玩相机"}]}]},{"type":"element","tag":"h3","props":{"id":"特殊技能演出"},"children":[{"type":"text","value":"特殊技能演出"}]},{"type":"element","tag":"ul","props":{},"children":[{"type":"element","tag":"li","props":{},"children":[{"type":"text","value":"尼禄的Devil Breaker部分招式有专属镜头"}]},{"type":"element","tag":"li","props":{},"children":[{"type":"text","value":"但丁的风格切换无特殊镜头变化"}]},{"type":"element","tag":"li","props":{},"children":[{"type":"text","value":"V的召唤兽终结技有短暂的特写镜头"}]},{"type":"element","tag":"li","props":{},"children":[{"type":"element","tag":"strong","props":{},"children":[{"type":"text","value":"Sin Devil Trigger"}]},{"type":"text","value":" 变身有专属的慢动作演出镜头"}]}]},{"type":"element","tag":"h2","props":{"id":"参数采集"},"children":[{"type":"text","value":"参数采集"}]},{"type":"element","tag":"table","props":{},"children":[{"type":"element","tag":"thead","props":{},"children":[{"type":"element","tag":"tr","props":{},"children":[{"type":"element","tag":"th","props":{},"children":[{"type":"text","value":"参数"}]},{"type":"element","tag":"th","props":{},"children":[{"type":"text","value":"探索"}]},{"type":"element","tag":"th","props":{},"children":[{"type":"text","value":"战斗(非锁定)"}]},{"type":"element","tag":"th","props":{},"children":[{"type":"text","value":"战斗(锁定)"}]}]}]},{"type":"element","tag":"tbody","props":{},"children":[{"type":"element","tag":"tr","props":{},"children":[{"type":"element","tag":"td","props":{},"children":[{"type":"text","value":"FOV"}]},{"type":"element","tag":"td","props":{},"children":[{"type":"text","value":"~60°"}]},{"type":"element","tag":"td","props":{},"children":[{"type":"text","value":"~65°"}]},{"type":"element","tag":"td","props":{},"children":[{"type":"text","value":"~65°"}]}]},{"type":"element","tag":"tr","props":{},"children":[{"type":"element","tag":"td","props":{},"children":[{"type":"text","value":"距离"}]},{"type":"element","tag":"td","props":{},"children":[{"type":"text","value":"~3.5m"}]},{"type":"element","tag":"td","props":{},"children":[{"type":"text","value":"~4.0m"}]},{"type":"element","tag":"td","props":{},"children":[{"type":"text","value":"~4.5m"}]}]},{"type":"element","tag":"tr","props":{},"children":[{"type":"element","tag":"td","props":{},"children":[{"type":"text","value":"高度偏移"}]},{"type":"element","tag":"td","props":{},"children":[{"type":"text","value":"+0.8m"}]},{"type":"element","tag":"td","props":{},"children":[{"type":"text","value":"+1.0m"}]},{"type":"element","tag":"td","props":{},"children":[{"type":"text","value":"+1.0m"}]}]},{"type":"element","tag":"tr","props":{},"children":[{"type":"element","tag":"td","props":{},"children":[{"type":"text","value":"跟随延迟"}]},{"type":"element","tag":"td","props":{},"children":[{"type":"text","value":"0.3s"}]},{"type":"element","tag":"td","props":{},"children":[{"type":"text","value":"0.15s"}]},{"type":"element","tag":"td","props":{},"children":[{"type":"text","value":"0.1s"}]}]},{"type":"element","tag":"tr","props":{},"children":[{"type":"element","tag":"td","props":{},"children":[{"type":"text","value":"回正速度"}]},{"type":"element","tag":"td","props":{},"children":[{"type":"text","value":"无自动回正"}]},{"type":"element","tag":"td","props":{},"children":[{"type":"text","value":"软回正 ~1s"}]},{"type":"element","tag":"td","props":{},"children":[{"type":"text","value":"无自动回正"}]}]}]}]},{"type":"element","tag":"blockquote","props":{},"children":[{"type":"element","tag":"p","props":{},"children":[{"type":"text","value":"以上数值为观察估算，非精确引擎数据"}]}]},{"type":"element","tag":"h2","props":{"id":"优缺点总结"},"children":[{"type":"text","value":"优缺点总结"}]},{"type":"element","tag":"h3","props":{"id":"优点"},"children":[{"type":"text","value":"优点"}]},{"type":"element","tag":"ul","props":{},"children":[{"type":"element","tag":"li","props":{},"children":[{"type":"text","value":"非锁定战斗体验流畅，不打断操作节奏"}]},{"type":"element","tag":"li","props":{},"children":[{"type":"text","value":"演出镜头华丽，强化了Stylish Action的表现力"}]},{"type":"element","tag":"li","props":{},"children":[{"type":"text","value":"软锁定设计在自由度和辅助之间取得了好平衡"}]}]},{"type":"element","tag":"h3","props":{"id":"缺点"},"children":[{"type":"text","value":"缺点"}]},{"type":"element","tag":"ul","props":{},"children":[{"type":"element","tag":"li","props":{},"children":[{"type":"text","value":"狭窄空间碰撞处理粗糙，偶尔\"吃镜头\""}]},{"type":"element","tag":"li","props":{},"children":[{"type":"text","value":"群战时偶尔看不到背后的敌人"}]},{"type":"element","tag":"li","props":{},"children":[{"type":"text","value":"固定机位遗产在少数区域造成视角突变"}]}]},{"type":"element","tag":"h3","props":{"id":"值得借鉴"},"children":[{"type":"text","value":"值得借鉴"}]},{"type":"element","tag":"ol","props":{},"children":[{"type":"element","tag":"li","props":{},"children":[{"type":"element","tag":"strong","props":{},"children":[{"type":"text","value":"软锁定概念"}]},{"type":"text","value":"：不强制锁定但自动辅助朝向，适合快节奏战斗"}]},{"type":"element","tag":"li","props":{},"children":[{"type":"element","tag":"strong","props":{},"children":[{"type":"text","value":"演出镜头无缝切入切出"}]},{"type":"text","value":"：不打断游玩节奏"}]},{"type":"element","tag":"li","props":{},"children":[{"type":"element","tag":"strong","props":{},"children":[{"type":"text","value":"锁定不劫持相机"}]},{"type":"text","value":"：锁定只改变角色朝向，相机仍可自由旋转"}]}]},{"type":"element","tag":"h2","props":{"id":"参考资料"},"children":[{"type":"text","value":"参考资料"}]},{"type":"element","tag":"ul","props":{},"children":[{"type":"element","tag":"li","props":{},"children":[{"type":"element","tag":"a","props":{"href":"https://www.youtube.com/watch?v=KMSGj9Y2T6Q","rel":["nofollow"]},"children":[{"type":"text","value":"DMC5 Official Gameplay - Capcom"}]}]},{"type":"element","tag":"li","props":{},"children":[{"type":"element","tag":"a","props":{"href":"https://example.com","rel":["nofollow"]},"children":[{"type":"text","value":"鬼泣5战斗系统解析 - 游戏机实用技术"}]}]}]}],"toc":{"title":"","searchDepth":2,"depth":2,"links":[{"id":"概述","depth":2,"text":"概述","children":[{"id":"核心设计理念","depth":3,"text":"核心设计理念"}]},{"id":"探索相机","depth":2,"text":"探索相机","children":[{"id":"跟随逻辑","depth":3,"text":"跟随逻辑"},{"id":"视角操控","depth":3,"text":"视角操控"},{"id":"碰撞处理","depth":3,"text":"碰撞处理"},{"id":"室内狭窄空间","depth":3,"text":"室内/狭窄空间"}]},{"id":"战斗相机","depth":2,"text":"战斗相机","children":[{"id":"锁定系统","depth":3,"text":"锁定系统"},{"id":"非锁定状态","depth":3,"text":"非锁定状态"},{"id":"目标切换","depth":3,"text":"目标切换"},{"id":"镜头抖动与反馈","depth":3,"text":"镜头抖动与反馈"}]},{"id":"特殊相机","depth":2,"text":"特殊相机","children":[{"id":"过场演出","depth":3,"text":"过场演出"},{"id":"qte处决","depth":3,"text":"QTE/处决"},{"id":"特殊技能演出","depth":3,"text":"特殊技能演出"}]},{"id":"参数采集","depth":2,"text":"参数采集"},{"id":"优缺点总结","depth":2,"text":"优缺点总结","children":[{"id":"优点","depth":3,"text":"优点"},{"id":"缺点","depth":3,"text":"缺点"},{"id":"值得借鉴","depth":3,"text":"值得借鉴"}]},{"id":"参考资料","depth":2,"text":"参考资料"}]}},"_type":"markdown","_id":"content:games:devil-may-cry.md","_source":"content","_file":"games/devil-may-cry.md","_stem":"games/devil-may-cry","_extension":"md"}